[
    {
        "text": "Welcome to Meta-Mind! I am your AI Architect. Let's take a quick tour.",
        "target": null
    },
    {
        "text": "Your main tools are tucked away here. Tap this button to expand the toolbar.",
        "target": "#btn-mobile-tools"
    },
    {
        "onEnter": "const tb = document.getElementById('top-toolbar'); if(tb && tb.classList.contains('hidden')) { tb.classList.remove('hidden'); tb.classList.add('flex'); }",
        "text": "Here is your main toolbar. You can add new nodes or auto-arrange your map here.",
        "target": "#top-toolbar"
    },
    {
        "onEnter": "const tb = document.getElementById('top-toolbar'); if(tb && !tb.classList.contains('hidden')) { tb.classList.add('hidden'); tb.classList.remove('flex'); }",
        "text": "This rail controls your current view Phase. Here you can switch between Map, Data, or Web modes.",
        "target": "#btn-phase-map",
        "animateToTarget": "#phase-selection-area"
    },
    {
        "text": "Need to edit a node's properties? Open the Inspector! Click the hamburger menu (or click Next to have me do it for you).",
        "conditionText": [
            {
                "condition": "document.getElementById('sidebar').classList.contains('open')",
                "text": "The Inspector is already open! This is where you edit node properties. Let's move on.",
                "autoClick": false
            }
        ],
        "target": "#btn-sidebar-toggle",
        "requireClick": false
    },
    {
        "text": "Use this search bar to quickly locate nodes in massive constellations.",
        "target": "#map-search-input"
    },
    {
        "text": "And I am always right here if you need me! You can ask me to generate entire map sections.",
        "target": "#ai-toggle-btn"
    }
]
